JianYingAutoClip/__init__.py
JianYingAutoClip/animation.py
JianYingAutoClip/audio_segment.py
JianYingAutoClip/draft_content_template.json
JianYingAutoClip/draft_folder.py
JianYingAutoClip/effect_segment.py
JianYingAutoClip/exceptions.py
JianYingAutoClip/jianying_controller.py
JianYingAutoClip/keyframe.py
JianYingAutoClip/local_materials.py
JianYingAutoClip/script_file.py
JianYingAutoClip/segment.py
JianYingAutoClip/template_mode.py
JianYingAutoClip/text_segment.py
JianYingAutoClip/time_util.py
JianYingAutoClip/track.py
JianYingAutoClip/util.py
JianYingAutoClip/video_segment.py
JianYingAutoClip/metadata/__init__.py
JianYingAutoClip/metadata/animation_meta.py
JianYingAutoClip/metadata/audio_effect_meta.py
JianYingAutoClip/metadata/effect_meta.py
JianYingAutoClip/metadata/filter_meta.py
JianYingAutoClip/metadata/font_meta.py
JianYingAutoClip/metadata/mask_meta.py
JianYingAutoClip/metadata/transition_meta.py
JianYingAutoClip/metadata/video_effect_meta.py
jianyingautoclip-0.0.1.dist-info/METADATA
jianyingautoclip-0.0.1.dist-info/WHEEL
jianyingautoclip-0.0.1.dist-info/top_level.txt
jianyingautoclip-0.0.1.dist-info/RECORD
